.DS_Store
asteriks/__init__.py
asteriks/asteriks.py
asteriks/build.py
asteriks/plotting.py
asteriks/query.py
asteriks/utils.py
asteriks/version.py
asteriks/data/lc_meta.p
asteriks/data/moving_objects.csv
asteriks/data/names-of-CAF-moving-objects.csv
asteriks/data/names-of-MAST-moving-objects.csv
asteriks/data/sc_meta.p
asteriks-0.3.dev1.dist-info/METADATA
asteriks-0.3.dev1.dist-info/RECORD
asteriks-0.3.dev1.dist-info/WHEEL
asteriks-0.3.dev1.dist-info/entry_points.txt
asteriks-0.3.dev1.dist-info/top_level.txt
