Metadata-Version: 2.1
Name: asteriks
Version: 0.3.dev1
Summary: Creates movies of Kepler/K2 asteroids based on target names. 
Home-page: UNKNOWN
Author: Christina Hedges
Author-email: christina.l.hedges@nasa.gov
License: MIT
Platform: UNKNOWN
Classifier: Development Status :: 3 - Alpha
Classifier: License :: OSI Approved :: MIT License
Classifier: Operating System :: OS Independent
Classifier: Programming Language :: Python :: 2.7
Classifier: Programming Language :: Python :: 3
Classifier: Intended Audience :: Science/Research
Classifier: Topic :: Scientific/Engineering :: Astronomy
Requires-Dist: astropy (>=0.4)
Requires-Dist: numpy
Requires-Dist: pandas
Requires-Dist: K2ephem
Requires-Dist: K2fov
Requires-Dist: fitsio
Requires-Dist: tqdm
